[
  {
    "title": "Indonesia's economy grows 5.39%, highest among G20 countries: Minister",
    "source": "https://en.antaranews.com/news/404094/indonesias-economy-grows-539-highest-among-g20-countries-minister",
    "timestamp": "2026-02-12 10:31:00"
  },
  {
    "title": "Indonesia's food stocks secured ahead of Ramadan, minister says",
    "source": "https://en.antaranews.com/news/404066/indonesias-food-stocks-secured-ahead-of-ramadan-minister-says",
    "timestamp": "2026-02-11 22:21:00"
  },
  {
    "title": "Prabowo to visit US for tariff deal, Board of Peace summit",
    "source": "https://en.antaranews.com/news/404054/prabowo-to-visit-us-for-tariff-deal-board-of-peace-summit",
    "timestamp": "2026-02-11 20:38:00"
  },
  {
    "title": "RI Govt aims to open Kayu Agung--Palembang--Betung toll before Eid",
    "source": "https://en.antaranews.com/news/404046/ri-govt-aims-to-open-kayu-agung-palembang-betung-toll-before-eid",
    "timestamp": "2026-02-11 20:03:00"
  },
  {
    "title": "Indonesia's SKK Migas to drill 100 exploration wells in 2026",
    "source": "https://en.antaranews.com/news/404030/indonesias-skk-migas-to-drill-100-exploration-wells-in-2026",
    "timestamp": "2026-02-11 19:25:00"
  },
  {
    "title": "Indonesia pursues food industry downstreaming to boost added value",
    "source": "https://en.antaranews.com/news/404010/indonesia-pursues-food-industry-downstreaming-to-boost-added-value",
    "timestamp": "2026-02-11 17:54:00"
  },
  {
    "title": "Ministry reviews Martabe gold mine permit status before revocation",
    "source": "https://en.antaranews.com/news/403982/ministry-reviews-martabe-gold-mine-permit-status-before-revocation",
    "timestamp": "2026-02-11 16:06:00"
  },
  {
    "title": "Danantara Indonesia seeks Saudi partnership on Hajj service boost",
    "source": "https://en.antaranews.com/news/403974/danantara-indonesia-seeks-saudi-partnership-on-hajj-service-boost",
    "timestamp": "2026-02-11 15:47:00"
  },
  {
    "title": "Indonesia invites Sinovac for long-term cooperation, investment",
    "source": "https://en.antaranews.com/news/403966/indonesia-invites-sinovac-for-long-term-cooperation-investment",
    "timestamp": "2026-02-11 15:29:00"
  },
  {
    "title": "Indonesia offers green hydrogen projects at GHES 2026 to lure capital",
    "source": "https://en.antaranews.com/news/403926/indonesia-offers-green-hydrogen-projects-at-ghes-2026-to-lure-capital",
    "timestamp": "2026-02-11 13:17:00"
  },
  {
    "title": "Gold edges lower on firmer dollar after strong US jobs data",
    "source": "https://www.thejakartapost.com/business/2026/02/12/gold-edges-lower-on-firmer-dollar-after-strong-us-jobs-data.html?utm_source=(direct)&utm_medium=channel_markets",
    "timestamp": "2026-02-12 00:00:00"
  },
  {
    "title": "Asian markets rally as Japan shares surge to record peak",
    "source": "https://www.thejakartapost.com/business/2026/02/09/asian-markets-rally-as-japan-shares-surge-to-record-peak.html?utm_source=(direct)&utm_medium=channel_markets",
    "timestamp": "2026-02-09 00:00:00"
  },
  {
    "title": "Presiden Komisaris Capitol Nusantara (CANI) Mengundurkan Diri",
    "source": "https://emitennews.com/news/presiden-komisaris-capitol-nusantara-cani-mengundurkan-diri",
    "timestamp": "2026-02-12 00:00:00"
  },
  {
    "title": "Bank Raya Catat 2,1 Juta Transaksi Pada Periode Program Pesta Raya",
    "source": "https://emitennews.com/news/bank-raya-catat-21-juta-transaksi-pada-periode-program-pesta-raya",
    "timestamp": "2026-02-12 00:00:00"
  },
  {
    "title": "Saham-Saham Ini Tampil Sangar, Usai Pertemuan 5 Konglo di Hambalang",
    "source": "https://emitennews.com/news/saham-saham-ini-tampil-sangar-usai-pertemuan-5-konglo-di-hambalang",
    "timestamp": "2026-02-12 00:00:00"
  },
  {
    "title": "Ekspansi ke IKN, Surge (WIFI) Gandeng BUMN Master Developer",
    "source": "https://emitennews.com/news/ekspansi-ke-ikn-surge-wifi-gandeng-bumn-master-developer",
    "timestamp": "2026-02-12 00:00:00"
  },
  {
    "title": "Sempat Molor, PSAB Tuntaskan Divestasi Tambang Emas Rp8,8 Triliun",
    "source": "https://emitennews.com/news/sempat-molor-psab-tuntaskan-divestasi-tambang-emas-rp88-triliun",
    "timestamp": "2026-02-12 00:00:00"
  },
  {
    "title": "Pendapatan Oke, Laba FUJI Terpangkas 24,29 Persen",
    "source": "https://emitennews.com/news/pendapatan-oke-laba-fuji-terpangkas-2429-persen",
    "timestamp": "2026-02-12 00:00:00"
  },
  {
    "title": "Melejit 127 Persen, UNVR Bukukan Laba Rp7,64 Triliun",
    "source": "https://emitennews.com/news/melejit-127-persen-unvr-bukukan-laba-rp764-triliun",
    "timestamp": "2026-02-12 00:00:00"
  },
  {
    "title": "Refinancing, PALM Tawarkan Obligasi Rp939 Miliar",
    "source": "https://emitennews.com/news/refinancing-palm-tawarkan-obligasi-rp939-miliar",
    "timestamp": "2026-02-12 00:00:00"
  },
  {
    "title": "Anjlok 15 Persen, Laba ELPI 2025 Sisa Rp213,3 Miliar",
    "source": "https://emitennews.com/news/anjlok-15-persen-laba-elpi-2025-sisa-rp2133-miliar",
    "timestamp": "2026-02-12 00:00:00"
  },
  {
    "title": "Prudent, BUKA Janji Habiskan Dana IPO Tahun Ini",
    "source": "https://emitennews.com/news/prudent-buka-janji-habiskan-dana-ipo-tahun-ini",
    "timestamp": "2026-02-12 00:00:00"
  },
  {
    "title": "Samuel Sekuritas Bungkus Saham FILM Rp5,06 Triliun",
    "source": "https://emitennews.com/news/samuel-sekuritas-bungkus-saham-film-rp506-triliun",
    "timestamp": "2026-02-12 00:00:00"
  },
  {
    "title": "Tumbuh Tipis, BNLI Catat Laba Bersih Rp3,58 Triliun",
    "source": "https://emitennews.com/news/tumbuh-tipis-bnli-catat-laba-bersih-rp358-triliun",
    "timestamp": "2026-02-12 00:00:00"
  },
  {
    "title": "Asing Net Buy, Saham REAL Bangkit dari Tekanan",
    "source": "https://emitennews.com/news/asing-net-buy-saham-real-bangkit-dari-tekanan",
    "timestamp": "2026-02-12 00:00:00"
  },
  {
    "title": "Jelang Jatuh Tempo Obligasi, BWPT Kunci Pembayaran Rp23,9 Miliar",
    "source": "https://emitennews.com/news/jelang-jatuh-tempo-obligasi-bwpt-kunci-pembayaran-rp239-miliar",
    "timestamp": "2026-02-11 00:00:00"
  },
  {
    "title": "Berdayakan Ultra Mikro, BTPS Raup Laba Rp1,2 Triliun",
    "source": "https://emitennews.com/news/berdayakan-ultra-mikro-btps-raup-laba-rp12-triliun",
    "timestamp": "2026-02-11 00:00:00"
  },
  {
    "title": "SMMA Tambah Amunisi Anak Usaha Rp800 Miliar, Bunga 8,25 Persen",
    "source": "https://emitennews.com/news/smma-tambah-amunisi-anak-usaha-rp800-miliar-bunga-825-persen",
    "timestamp": "2026-02-11 00:00:00"
  },
  {
    "title": "Mandiri Terang Divestasi 4,52 Persen Saham PEGE, Nilainya Rp23,15M",
    "source": "https://emitennews.com/news/mandiri-terang-divestasi-452-persen-saham-pege-nilainya-rp2315m",
    "timestamp": "2026-02-11 00:00:00"
  },
  {
    "title": "Free Float Lebar, Investor GPSO Bertambah Usai Rencana Akuisisi Jumbo",
    "source": "https://emitennews.com/news/free-float-lebar-investor-gpso-bertambah-usai-rencana-akuisisi-jumbo",
    "timestamp": "2026-02-11 00:00:00"
  },
  {
    "title": "IHSG SESI I DITUTUP MELEMAH 31 POIN DI LEVEL 8.259",
    "timestamp": "2026-02-11 22:09:59",
    "source": "https://bcasekuritas.co.id/en/latest-news/news/ihsg-sesi-i-ditutup-melemah-31-poin-di-level-8259"
  },
  {
    "title": "PERTAMINA HULU INDONESIA LAMPAUI TARGET PRODUKSI MIGAS 2025",
    "timestamp": "2026-02-11 21:58:53",
    "source": "https://bcasekuritas.co.id/en/latest-news/news/pertamina-hulu-indonesia-lampaui-target-produksi-migas-2025"
  },
  {
    "title": "KAI PASTIKAN KESIAPAN ANGKUTAN LEBARAN 2026 DI DAOP 6",
    "timestamp": "2026-02-11 21:54:24",
    "source": "https://bcasekuritas.co.id/en/latest-news/news/kai-pastikan-kesiapan-angkutan-lebaran-2026-di-daop-6"
  },
  {
    "title": "AIRASIA SEBUT INDONESIA JADI PASAR ANDALAN DI RUTE INTERNASIONAL",
    "timestamp": "2026-02-11 21:42:27",
    "source": "https://bcasekuritas.co.id/en/latest-news/news/airasia-sebut-indonesia-jadi-pasar-andalan-di-rute-internasional"
  },
  {
    "title": "IFG : KENAIKAN LIMIT INVESTASI DAPEN-ASURANSI PERLU MITIGASI RISIKO",
    "timestamp": "2026-02-11 21:33:27",
    "source": "https://bcasekuritas.co.id/en/latest-news/news/ifg-kenaikan-limit-investasi-dapen-asuransi-perlu-mitigasi-risiko"
  },
  {
    "title": "MENDAG : EKSPOR ACEH TEMBUS 59,60 JUTA DOLAR, SUMBAR NAIK 27,64 PERSEN",
    "timestamp": "2026-02-11 21:24:58",
    "source": "https://bcasekuritas.co.id/en/latest-news/news/mendag-ekspor-aceh-tembus-5960-juta-dolar-sumbar-naik-2764-persen"
  },
  {
    "title": "PERKUAT STRUKTUR MODAL, CNKO UMUMKAN PENINGKATAN MODAL ANAK USAHA SENILAI RP32,7 MILIAR",
    "timestamp": "2026-02-11 21:12:49",
    "source": "https://bcasekuritas.co.id/en/latest-news/news/perkuat-struktur-modal-cnko-umumkan-peningkatan-modal-anak-usaha-senilai-rp327-miliar"
  },
  {
    "title": "PELNI RESMI BUKA PENJUALAN TIKET LEBARAN 2026",
    "timestamp": "2026-02-11 21:05:28",
    "source": "https://bcasekuritas.co.id/en/latest-news/news/pelni-resmi-buka-penjualan-tiket-lebaran-2026"
  },
  {
    "title": "BIO FARMA TEGASKAN KOMITMEN KEMANDIRIAN VAKSIN OKI",
    "timestamp": "2026-02-11 21:00:32",
    "source": "https://bcasekuritas.co.id/en/latest-news/news/bio-farma-tegaskan-komitmen-kemandirian-vaksin-oki"
  },
  {
    "title": "MYOH PERKUAT MODAL DI ANAK USAHANYA \n",
    "timestamp": "2026-02-11 20:47:24",
    "source": "https://bcasekuritas.co.id/en/latest-news/news/myoh-perkuat-modal-di-anak-usahanya"
  },
  {
    "title": "ITDC HADIRKAN PROGRAM SPESIAL IMLEK",
    "timestamp": "2026-02-11 20:34:01",
    "source": "https://bcasekuritas.co.id/en/latest-news/news/itdc-hadirkan-program-spesial-imlek"
  },
  {
    "title": "BUDI TJAHJADI LEPAS  KEPEMILIKAN SAHAM FWCT\n",
    "timestamp": "2026-02-11 20:29:06",
    "source": "https://bcasekuritas.co.id/en/latest-news/news/budi-tjahjadi-lepas-kepemilikan-saham-fwct"
  }
]