[
    {
        "title": "Foreigners sell almost 12 billion shares, net selling 2.90 billion",
        "source": "https://www.idnfinancials.com/news/63417/foreigners-sell-almost-12-billion-shares-net-selling-2-90-billion",
        "timestamp": "2026-04-30 18:00:31"
    },
    {
        "title": "JCI falls 2.42% for the week, rupiah steadies at IDR 17,346 per USD",
        "source": "https://www.idnfinancials.com/news/63414/jci-falls-2-42-for-the-week-rupiah-steadies-at-idr-17-346-per-usd",
        "timestamp": "2026-04-30 16:55:20"
    },
    {
        "title": "JCI faces profit-taking, oil price surge",
        "source": "https://www.idnfinancials.com/news/63391/jci-faces-profit-taking-oil-price-surge",
        "timestamp": "2026-04-30 07:32:11"
    },
    {
        "title": "Foreign trading strengthens, net selling 779 million shares",
        "source": "https://www.idnfinancials.com/news/63384/foreign-trading-strengthens-net-selling-779-million-shares",
        "timestamp": "2026-04-29 17:43:18"
    },
    {
        "title": "JCI rises 28.83 points, watch profit-taking ahead of long weekend",
        "source": "https://www.idnfinancials.com/news/63381/jci-rises-28-83-points-watch-profit-taking-ahead-of-long-weekend",
        "timestamp": "2026-04-29 16:56:21"
    },
    {
        "title": "BNY Mellon raises stakes in TLKM, Henan Putihrai accumulates SSIA",
        "source": "https://www.idnfinancials.com/news/63370/bny-mellon-raises-stakes-in-tlkm-henan-putihrai-accumulates-ssia",
        "timestamp": "2026-04-29 12:50:32"
    },
    {
        "title": "JCI edges up in first session, rupiah breaches IDR 17,341/USD",
        "source": "https://www.idnfinancials.com/news/63371/jci-edges-up-in-first-session-rupiah-breaches-idr-17-341usd",
        "timestamp": "2026-04-29 13:18:39"
    },
    {
        "title": "SINI eyes standby buyers, will Prajogo Pangestu\u2019s CUAN step in?",
        "source": "https://www.idnfinancials.com/news/63368/sini-eyes-standby-buyers-will-prajogo-pangestus-cuan-step-in",
        "timestamp": "2026-04-29 11:15:05"
    },
    {
        "title": "GoTo posts maiden profit of Rp257.9 billion in Q1 2026",
        "source": "https://www.idnfinancials.com/news/63349/goto-posts-maiden-profit-of-rp257-9-billion-in-q1-2026",
        "timestamp": "2026-04-28 20:20:54"
    },
    {
        "title": "Slow foreign trading, net sell down to 1.38 billion shares",
        "source": "https://www.idnfinancials.com/news/63348/slow-foreign-trading-net-sell-down-to-1-38-billion-shares",
        "timestamp": "2026-04-28 17:48:33"
    },
    {
        "title": "JCI slips 0.15% in first session as foreign funds exit bank stocks",
        "source": "https://www.idnfinancials.com/news/63335/jci-slips-0-15-in-first-session-as-foreign-funds-exit-bank-stocks",
        "timestamp": "2026-04-28 12:59:08"
    },
    {
        "title": "Three years at loss, PYFA seeks fresh capital through rights issue",
        "source": "https://www.idnfinancials.com/news/63330/three-years-at-loss-pyfa-seeks-fresh-capital-through-rights-issue",
        "timestamp": "2026-04-28 09:47:31"
    },
    {
        "title": "Foreign selling dominates, risk of JCI testing 7,000 still opens up",
        "source": "https://www.idnfinancials.com/news/63326/foreign-selling-dominates-risk-of-jci-testing-7-000-still-opens-up",
        "timestamp": "2026-04-28 08:40:32"
    },
    {
        "title": "Foreign buying weakens, net sell surges to 1.61 billion shares",
        "source": "https://www.idnfinancials.com/news/63312/foreign-buying-weakens-net-sell-surges-to-1-61-billion-shares",
        "timestamp": "2026-04-27 18:24:51"
    },
    {
        "title": "Foreign investors sell bank stocks as JCI rises 0.65% in first session",
        "source": "https://www.idnfinancials.com/news/63307/foreign-investors-sell-bank-stocks-as-jci-rises-0-65-in-first-session",
        "timestamp": "2026-04-27 13:36:28"
    },
    {
        "title": "JCI falls 6.59% weekly, set to test key support levels?",
        "source": "https://www.idnfinancials.com/news/63293/jci-falls-6-59-weekly-set-to-test-key-support-levels",
        "timestamp": "2026-04-27 09:00:34"
    },
    {
        "title": "IDX reshuffles LQ45 and IDX80, BREN and DSSA out",
        "source": "https://www.idnfinancials.com/news/63264/idx-reshuffles-lq45-and-idx80-bren-and-dssa-out",
        "timestamp": "2026-04-24 21:27:32"
    },
    {
        "title": "Despite stronger foreign buying, net sell still at 475 million shares",
        "source": "https://www.idnfinancials.com/news/63261/despite-stronger-foreign-buying-net-sell-still-at-475-million-shares",
        "timestamp": "2026-04-24 17:54:14"
    },
    {
        "title": "BNY Mellon keeps accumulating TLKM shares, Henan Putihrai buys SSIA",
        "source": "https://www.idnfinancials.com/news/63253/bny-mellon-keeps-accumulating-tlkm-shares-henan-putihrai-buys-ssia",
        "timestamp": "2026-04-24 14:03:45"
    },
    {
        "title": "BNY Mellon adds 18.97M TLKM shares, lifting its stake to 5.67%",
        "source": "https://www.idnfinancials.com/news/63214/bny-mellon-adds-18-97m-tlkm-shares-lifting-its-stake-to-5-67",
        "timestamp": "2026-04-23 13:44:23"
    },
    {
        "title": "Intip Rincian Surat Berharga Syariah Negara Target Rp12 Triliun Lelang Selasa (5/5)",
        "source": "https://market.bisnis.com/read/20260503/92/1970905/intip-rincian-surat-berharga-syariah-negara-target-rp12-triliun-lelang-selasa-55",
        "timestamp": "2026-05-03 05:11:39"
    },
    {
        "title": "Siap-Siap Jadwal Cum Dividen Saham Astra (ASII) 2026 Senin (4/5)",
        "source": "https://market.bisnis.com/read/20260503/7/1970900/siap-siap-jadwal-cum-dividen-saham-astra-asii-2026-senin-45",
        "timestamp": "2026-05-03 04:11:39"
    },
    {
        "title": "Harga Emas Perhiasan Hari Ini 3 Mei 2026 Merosot Lagi",
        "source": "https://market.bisnis.com/read/20260503/235/1970883/harga-emas-perhiasan-hari-ini-3-mei-2026-merosot-lagi",
        "timestamp": "2026-05-03 02:11:39"
    },
    {
        "title": "Harga Emas Antam Logam Mulia 3 Mei 2026 Sentuh Rp2,79 Juta per Gram",
        "source": "https://market.bisnis.com/read/20260503/235/1970881/harga-emas-antam-logam-mulia-3-mei-2026-sentuh-rp279-juta-per-gram",
        "timestamp": "2026-05-03 02:11:39"
    },
    {
        "title": "Harga Buyback Emas Antam di Pegadaian Hari Ini Minggu 3 Mei 2026",
        "source": "https://market.bisnis.com/read/20260503/235/1970880/harga-buyback-emas-antam-di-pegadaian-hari-ini-minggu-3-mei-2026",
        "timestamp": "2026-05-03 02:11:39"
    },
    {
        "title": "Harga Emas UBS & Galeri 24 di Pegadaian Hari Ini Minggu 3 Mei 2026",
        "source": "https://market.bisnis.com/read/20260503/235/1970878/harga-emas-ubs-galeri-24-di-pegadaian-hari-ini-minggu-3-mei-2026",
        "timestamp": "2026-05-03 00:11:39"
    },
    {
        "title": "Harga Emas Antam di Pegadaian Hari Ini Minggu 3 Mei 2026",
        "source": "https://market.bisnis.com/read/20260503/235/1970866/harga-emas-antam-di-pegadaian-hari-ini-minggu-3-mei-2026",
        "timestamp": "2026-05-03 00:11:39"
    },
    {
        "title": "Bukit Asam (PTBA) Bukukan Laba Bersih Rp801,79 Miliar pada Kuartal I/2026",
        "source": "https://market.bisnis.com/read/20260502/192/1970836/bukit-asam-ptba-bukukan-laba-bersih-rp80179-miliar-pada-kuartal-i2026",
        "timestamp": "2026-05-02 10:11:39"
    },
    {
        "title": "Medco Energi (MEDC) Raup Laba Bersih Rp1,16 Triliun, Melonjak 282% Kuartal I/2026",
        "source": "https://market.bisnis.com/read/20260502/192/1970821/medco-energi-medc-raup-laba-bersih-rp116-triliun-melonjak-282-kuartal-i2026",
        "timestamp": "2026-05-02 09:11:39"
    },
    {
        "title": "IHSG Tinggalkan 7.000, Peluang Akumulasi Saham Murah",
        "source": "https://market.bisnis.com/read/20260502/7/1970826/ihsg-tinggalkan-7000-peluang-akumulasi-saham-murah",
        "timestamp": "2026-05-02 08:11:39"
    },
    {
        "title": "PNM Perluas Akses Pendidikan hingga Pelosok Negeri",
        "source": "https://market.bisnis.com/read/20260502/192/1970807/pnm-perluas-akses-pendidikan-hingga-pelosok-negeri",
        "timestamp": "2026-05-02 10:42:00"
    },
    {
        "title": "IHSG Lesu: Saham DSSA, BBCA hingga BREN Masuk Daftar Top Laggards",
        "source": "https://market.bisnis.com/read/20260502/7/1970801/ihsg-lesu-saham-dssa-bbca-hingga-bren-masuk-daftar-top-laggards",
        "timestamp": "2026-05-02 09:59:00"
    },
    {
        "title": "Saham EMAS, MDKA hingga AADI Jadi Dinamo IHSG 4 Bulan Terakhir",
        "source": "https://market.bisnis.com/read/20260502/7/1970795/saham-emas-mdka-hingga-aadi-jadi-dinamo-ihsg-4-bulan-terakhir",
        "timestamp": "2026-05-02 09:28:00"
    },
    {
        "title": "Danantara Jadi Pemegang Saham Ojol, Analis Sebut Keuntungannya",
        "source": "https://market.bisnis.com/read/20260502/192/1970800/danantara-jadi-pemegang-saham-ojol-analis-sebut-keuntungannya",
        "timestamp": "2026-05-02 09:27:00"
    },
    {
        "title": "Harga Emas Antam Logam Mulia 2 Mei 2026 Turun Jadi Rp2,79 Juta/Gram",
        "source": "https://market.bisnis.com/read/20260502/235/1970796/harga-emas-antam-logam-mulia-2-mei-2026-turun-jadi-rp279-jutagram",
        "timestamp": "2026-05-02 09:01:00"
    },
    {
        "title": "Rapor Hijau Keuangan Emiten Prajogo Pangestu Kuartal I/2026",
        "source": "https://market.bisnis.com/read/20260502/192/1970793/rapor-hijau-keuangan-emiten-prajogo-pangestu-kuartal-i2026",
        "timestamp": "2026-05-02 08:45:00"
    },
    {
        "title": "Harga Buyback Emas Antam di Pegadaian Hari Ini Sabtu 2 Mei 2026",
        "source": "https://market.bisnis.com/read/20260502/235/1970789/harga-buyback-emas-antam-di-pegadaian-hari-ini-sabtu-2-mei-2026",
        "timestamp": "2026-05-02 07:34:00"
    },
    {
        "title": "Harga Emas Perhiasan Hari Ini 2 Mei 2026 Naik Tipis",
        "source": "https://market.bisnis.com/read/20260502/235/1970756/harga-emas-perhiasan-hari-ini-2-mei-2026-naik-tipis",
        "timestamp": "2026-05-02 07:33:00"
    },
    {
        "title": "Harga Emas UBS & Galeri 24 di Pegadaian Hari Ini Sabtu 2 Mei 2026",
        "source": "https://market.bisnis.com/read/20260502/235/1970788/harga-emas-ubs-galeri-24-di-pegadaian-hari-ini-sabtu-2-mei-2026",
        "timestamp": "2026-05-02 07:25:00"
    },
    {
        "title": "Harga Emas Antam di Pegadaian Hari Ini Sabtu 2 Mei 2026",
        "source": "https://market.bisnis.com/read/20260502/235/1970787/harga-emas-antam-di-pegadaian-hari-ini-sabtu-2-mei-2026",
        "timestamp": "2026-05-02 07:18:00"
    },
    {
        "title": "Jababeka (KIJA) Raup Marketing Sales Rp540 Miliar per Kuartal I/2026, Genjot Segmen Logistik",
        "source": "https://market.bisnis.com/read/20260502/192/1970743/jababeka-kija-raup-marketing-sales-rp540-miliar-per-kuartal-i2026-genjot-segmen-logistik",
        "timestamp": "2026-05-02 03:07:00"
    },
    {
        "title": "Laba Melemah di Kuartal I/2026, Summarecon Agung (SMRA) Berharap Pemulihan Kelas Menengah",
        "source": "https://market.bisnis.com/read/20260502/192/1970747/laba-melemah-di-kuartal-i2026-summarecon-agung-smra-berharap-pemulihan-kelas-menengah",
        "timestamp": "2026-05-02 00:03:00"
    },
    {
        "title": "BREN Raup Laba Bersih Rp728,98 Miliar pada Kuartal I/2026",
        "source": "https://market.bisnis.com/read/20260501/192/1970694/bren-raup-laba-bersih-rp72898-miliar-pada-kuartal-i2026",
        "timestamp": "2026-05-01 18:30:00"
    },
    {
        "title": "Mr. D.I.Y. (MDIY) Masuk Jadi Investor Non Pengendali di KKV",
        "source": "https://market.bisnis.com/read/20260501/192/1970707/mr-diy-mdiy-masuk-jadi-investor-non-pengendali-di-kkv",
        "timestamp": "2026-05-01 17:39:00"
    },
    {
        "title": "Pendapatan Naik 73,6%, CUAN Raup Laba Bersih US$5,69 Juta pada Kuartal I/2026",
        "source": "https://market.bisnis.com/read/20260501/7/1970699/pendapatan-naik-736-cuan-raup-laba-bersih-us569-juta-pada-kuartal-i2026",
        "timestamp": "2026-05-01 17:37:00"
    },
    {
        "title": "Samudera Indonesia (SMDR) Bocorkan Nilai Pembagian Dividen Final, Segini Nilainya",
        "source": "https://market.bisnis.com/read/20260501/192/1970697/samudera-indonesia-smdr-bocorkan-nilai-pembagian-dividen-final-segini-nilainya",
        "timestamp": "2026-05-01 16:41:00"
    },
    {
        "title": "Emiten Farmasi PYFA Target Rights Issue Tuntas Kuartal III/2026",
        "source": "https://market.bisnis.com/read/20260501/192/1970712/emiten-farmasi-pyfa-target-rights-issue-tuntas-kuartal-iii2026",
        "timestamp": "2026-05-01 16:35:00"
    },
    {
        "title": "Emiten Prajogo Pangestu CDIA Cetak Laba Rp142,37 Miliar Kuartal I/2026",
        "source": "https://market.bisnis.com/read/20260501/192/1970688/emiten-prajogo-pangestu-cdia-cetak-laba-rp14237-miliar-kuartal-i2026",
        "timestamp": "2026-05-01 14:50:00"
    },
    {
        "title": "Arah IHSG Pekan Depan Ditentukan Rilis Data Ekonomi",
        "source": "https://market.bisnis.com/read/20260501/189/1970615/arah-ihsg-pekan-depan-ditentukan-rilis-data-ekonomi",
        "timestamp": "2026-05-01 14:20:00"
    },
    {
        "title": "Laba Bersih BRPT Meroket 459% jadi Rp1,53 Triliun Kuartal I/2026",
        "source": "https://market.bisnis.com/read/20260501/192/1970671/laba-bersih-brpt-meroket-459-jadi-rp153-triliun-kuartal-i2026",
        "timestamp": "2026-05-01 13:16:00"
    },
    {
        "title": "Gudang Garam (GGRM) Beri Kejutan, Saham Siap Sprint",
        "source": "https://investor.id/stock/437657/gudang-garam-ggrm-beri-kejutan-saham-siap-sprint",
        "timestamp": "2026-05-03 13:01:00"
    },
    {
        "title": "Saham ADRO Dikeker, Cara Cuan Cepat Diungkap",
        "source": "https://investor.id/stock/437655/saham-adro-dikeker-cara-cuan-cepat-diungkap",
        "timestamp": "2026-05-03 12:03:00"
    },
    {
        "title": "Isu Panas Saham Bank",
        "source": "https://investor.id/stock/437652/isu-panas-saham-bank",
        "timestamp": "2026-05-03 10:07:00"
    },
    {
        "title": "Saham BBNI Malah Diburu, Harga Bisa Segini",
        "source": "https://investor.id/stock/437649/saham-bbni-malah-diburu-harga-bisa-segini",
        "timestamp": "2026-05-03 09:02:00"
    },
    {
        "title": "Saham BUMI Membalikkan Keadaan",
        "source": "https://investor.id/stock/437617/saham-bumi-membalikkan-keadaan",
        "timestamp": "2026-05-02 19:00:00"
    },
    {
        "title": "Saham Mumpung Murah, Dividennya Rp 376,95 per Saham",
        "source": "https://investor.id/stock/437599/saham-mumpung-murah-dividennya-rp-37695-per-saham",
        "timestamp": "2026-05-02 14:02:00"
    },
    {
        "title": "Alarm Saham BBCA Mulai Berbunyi, Situasi Bisa Berbalik?",
        "source": "https://investor.id/stock/437613/alarm-saham-bbca-mulai-berbunyi-situasi-bisa-berbalik",
        "timestamp": "2026-05-02 12:36:00"
    },
    {
        "title": "Kejadian Langka di Saham Emiten Anthoni Salim",
        "source": "https://investor.id/stock/437598/kejadian-langka-di-saham-emiten-anthoni-salim",
        "timestamp": "2026-05-02 08:33:00"
    },
    {
        "title": "Sudah Terbang 384%, Saham Diramal Masih Bisa Naik 138%",
        "source": "https://investor.id/stock/437583/sudah-terbang-384-saham-diramal-masih-bisa-naik-138",
        "timestamp": "2026-05-01 20:55:00"
    },
    {
        "title": "Saham-saham Penyangga Laju\u00a0Pasar",
        "source": "https://investor.id/stock/437547/sahamsaham-penyangga-lajupasar",
        "timestamp": "2026-05-01 17:00:00"
    },
    {
        "title": "Barisan Saham yang Bikin Investor Tekor",
        "source": "https://investor.id/stock/437541/barisan-saham-yang-bikin-investor-tekor",
        "timestamp": "2026-05-01 16:00:00"
    },
    {
        "title": "Deretan Saham Pemberi Cuan Jumbo",
        "source": "https://investor.id/stock/437539/deretan-saham-pemberi-cuan-jumbo",
        "timestamp": "2026-05-01 15:00:00"
    },
    {
        "title": "List Saham Obralan Investor Asing",
        "source": "https://investor.id/stock/437519/list-saham-obralan-investor-asing",
        "timestamp": "2026-05-01 11:00:00"
    },
    {
        "title": "Saham Penyedot Duit Asing",
        "source": "https://investor.id/stock/437514/saham-penyedot-duit-asing",
        "timestamp": "2026-05-01 09:30:00"
    },
    {
        "title": "Jatuhnya IHSG Bikin\u00a0Market Cap Menguap Rp 354 Triliun",
        "source": "https://investor.id/stock/437509/jatuhnya-ihsg-bikinmarket-cap-menguap-rp-354-triliun",
        "timestamp": "2026-05-01 08:00:00"
    },
    {
        "title": "BERITA POPULER: Aksi Borong Emas hingga Aguan Blak-blakan soal PIK2 (PANI)",
        "source": "https://investor.id/stock/437501/berita-populer-aksi-borong-emas-hingga-aguan-blakblakan-soal-pik2-pani",
        "timestamp": "2026-05-01 06:00:00"
    },
    {
        "title": "Wall Street Melonjak Tajam, S&P 500 Tembus Rekor di Atas 7.200",
        "source": "https://investor.id/stock/437499/wall-street-melonjak-tajam-sp-500-tembus-rekor-di-atas-7200",
        "timestamp": "2026-05-01 05:20:00"
    },
    {
        "title": "Net Sell Asing Nyaris Rp 50 Triliun, 5 Saham Dihantam",
        "source": "https://investor.id/stock/437482/net-sell-asing-nyaris-rp-50-triliun-5-saham-dihantam",
        "timestamp": "2026-04-30 21:20:00"
    },
    {
        "title": "Laba Adira Finance (ADMF) Tersengat Efek Merger",
        "source": "https://investor.id/stock/437462/laba-adira-finance-admf-tersengat-efek-merger",
        "timestamp": "2026-04-30 18:57:00"
    },
    {
        "title": "CIMB Niaga (BNGA) Raup\u00a0Laba Rp1,76 Triliun",
        "source": "https://investor.id/stock/437447/cimb-niaga-bnga-rauplaba-rp176-triliun",
        "timestamp": "2026-04-30 17:25:00"
    },
    {
        "title": "United Tractors Menunjuk Presdir Dan Preskom Yang Baru Pada RUPST 2026",
        "source": "https://www.indonesiancoalandnickel.com/united-tractors-menunjuk-presdir-dan-preskom-yang-baru-pada-rupst-2026/",
        "timestamp": "2026-04-17 00:00:00"
    },
    {
        "title": "United Tractors Bagikan Dividen Rp 5,92 Triliun dan Angkat Komisaris Serta Direksi Baru di RUPST 2026",
        "source": "https://www.indonesiancoalandnickel.com/united-tractors-bagikan-dividen-rp-592-triliun-dan-angkat-komisaris-serta-direksi-baru-di-rupst-2026/",
        "timestamp": "2026-04-17 00:00:00"
    },
    {
        "title": "PT United Tractors Tbk Tetapkan Dividen Tunai Rp 1.663 per Lembar Saham dan Angkat Komisaris serta Direksi Baru dalam RUPST 2026",
        "source": "https://www.indonesiancoalandnickel.com/pt-united-tractors-tbk-tetapkan-dividen-tunai-rp-1-663-per-lembar-saham-dan-angkat-komisaris-serta-direksi-baru-dalam-rupst-2026/",
        "timestamp": "2026-04-17 00:00:00"
    },
    {
        "title": "Grup United Tractors Gelar Mudik Bersama 2026 \u201cMudik Penuh Makna Bersama Scania\u201d",
        "source": "https://www.indonesiancoalandnickel.com/grup-united-tractors-gelar-mudik-bersama-2026-mudik-penuh-makna-bersama-scania/",
        "timestamp": "2026-03-18 00:00:00"
    },
    {
        "title": "United Tractors Perkuat Kolaborasi Pendidikan Vokasi dengan Kemendikdasmen",
        "source": "https://www.indonesiancoalandnickel.com/united-tractors-perkuat-kolaborasi-pendidikan-vokasi-dengan-kemendikdasmen/",
        "timestamp": "2026-03-13 00:00:00"
    },
    {
        "title": "Presiden Direktur Bina Pertiwi Raih Penghargaan Indonesia Best CEO Awards 2025",
        "source": "https://www.indonesiancoalandnickel.com/presiden-direktur-bina-pertiwi-raih-penghargaan-indonesia-best-ceo-awards-2025/",
        "timestamp": "2026-03-13 00:00:00"
    },
    {
        "title": "MET CONNEX 2026 : Kolaborasi Strategis Mining & Metallurgy Untuk Perkuat Ekosistem Pengolahan Mineral Indonesia",
        "source": "https://www.indonesiancoalandnickel.com/met-connex-2026-kolaborasi-strategis-mining-metallurgy/",
        "timestamp": "2026-03-06 00:00:00"
    },
    {
        "title": "Dari Lereng Gunung Arjuno, United Tractors Bangun Ketahanan Masyarakat melalui Program Desa UniTy",
        "source": "https://www.indonesiancoalandnickel.com/dari-lereng-gunung-arjuno-united-tractors-bangun-ketahanan-masyarakat-melalui-program-desa-unity/",
        "timestamp": "2026-03-03 00:00:00"
    },
    {
        "title": "Komatsu Remanufacturing Asia Raih INDI 4.0 Smart Factory dari Kementerian Perindustrian Republik Indonesia",
        "source": "https://www.indonesiancoalandnickel.com/komatsu-remanufacturing-asia-raih-indi-4-0-smart-factory-dari-kementerian-perindustrian-republik-indonesia/",
        "timestamp": "2026-03-03 00:00:00"
    },
    {
        "title": "United Tractors Membukukan Laba Bersih Sebesar Rp14,8 Triliun di Tahun 2025",
        "source": "https://www.indonesiancoalandnickel.com/united-tractors-membukukan-laba-bersih-sebesar-rp148-triliun-di-tahun-2025/",
        "timestamp": "2026-02-27 00:00:00"
    },
    {
        "title": "PLTM Kukusan 2 Resmi Beroperasi, Arkora Hydro Tambah Kapasitas Energi Bersih",
        "source": "https://www.indonesiancoalandnickel.com/pltm-kukusan-2-resmi-beroperasi-arkora-hydro-tambah-kapasitas-energi-bersih/",
        "timestamp": "2026-02-26 00:00:00"
    },
    {
        "title": "United Tractors Berbagi Ilmu dan Serahkan Alat Praktik Pertanian di Universitas Diponegoro",
        "source": "https://www.indonesiancoalandnickel.com/united-tractors-berbagi-ilmu-dan-serahkan-alat-praktik-pertanian-di-universitas-diponegoro/",
        "timestamp": "2026-02-26 00:00:00"
    },
    {
        "title": "Terlindungi: Laporan Keuangan Resource Alam Indonesia",
        "source": "https://www.indonesiancoalandnickel.com/laporan-keuangan-resource-alam-indonesia/",
        "timestamp": "2024-07-01 00:00:00"
    },
    {
        "title": "Laporan Keuangan Delta Dunia Makmur",
        "source": "https://www.indonesiancoalandnickel.com/laporan-keuangan-delta-dunia-makmur/",
        "timestamp": "2024-07-01 00:00:00"
    },
    {
        "title": "Laporan Keuangan Adaro",
        "source": "https://www.indonesiancoalandnickel.com/laporan-keuangan-adaro/",
        "timestamp": "2024-07-01 00:00:00"
    },
    {
        "title": "Anticipating Drought, GAPKI Strengthens Fire-Prevention System",
        "source": "https://gapki.id/en/news/2026/04/28/anticipating-drought-gapki-strengthens-fire-prevention-system/",
        "timestamp": "2026-04-30 13:37:45"
    },
    {
        "title": "RI Sets Up ASEAN Center For Transboundary Haze Control",
        "source": "https://gapki.id/en/news/2026/04/27/ri-sets-up-asean-center-for-transboundary-haze-control/",
        "timestamp": "2026-04-29 12:34:46"
    },
    {
        "title": "Fully Relying On B50, RI To Stop Diesel Fuel Import Since July",
        "source": "https://gapki.id/en/news/2026/04/23/fully-relying-on-b50-ri-to-stop-diesel-fuel-import-since-july/",
        "timestamp": "2026-04-24 15:58:06"
    },
    {
        "title": "Palm Oil Performance In February 2026 Rises: Production, Consumption, Exports Up, Stock declines",
        "source": "https://gapki.id/en/news/2026/04/22/palm-oil-performance-in-february-2026-rises-production-consumption-exports-up-stock-declines/",
        "timestamp": "2026-04-24 15:57:22"
    },
    {
        "title": "FEATURE: Palm Oil: High Versatility That Follows Human Activities All Day",
        "source": "https://gapki.id/en/news/2026/04/21/feature-palm-oil-high-versatility-that-follows-human-activities-all-day/",
        "timestamp": "2026-04-24 15:18:18"
    },
    {
        "title": "Govt To Push Palm Expansion Through Use of Marginal Lands",
        "source": "https://gapki.id/en/news/2026/04/20/govt-to-push-palm-expansion-through-use-of-marginal-lands/",
        "timestamp": "2026-04-23 12:36:35"
    },
    {
        "title": "RI Has Huge Potential Of Palm Wastes, But Not Yet Optimized",
        "source": "https://gapki.id/en/news/2026/04/17/ri-has-huge-potential-of-palm-wastes-but-not-yet-optimized/",
        "timestamp": "2026-04-23 12:37:28"
    },
    {
        "title": "Expert: Cattle-Palm Integration Can Increase Palm Sustainability",
        "source": "https://gapki.id/en/news/2026/04/14/expert-cattle-palm-integration-can-increase-palm-sustainability/",
        "timestamp": "2026-04-14 14:43:40"
    },
    {
        "title": "RI To Build Biorefineries To Produce Bioavtur From Palm Oil, UCO",
        "source": "https://gapki.id/en/news/2026/04/13/ri-to-build-biorefineries-to-produce-bioavtur-from-palm-oil-uco/",
        "timestamp": "2026-04-14 14:03:38"
    },
    {
        "title": "RI Introduces New Pollinator Insects To Raise Palm Productivity",
        "source": "https://gapki.id/en/news/2026/04/12/ri-introduces-new-pollinator-insects-to-raise-palm-productivity/",
        "timestamp": "2026-04-14 10:12:57"
    },
    {
        "title": "Percepat Perizinan, Ditjen Minerba Gelar Coaching Clinic RKAB",
        "source": "https://www.minerba.esdm.go.id/berita/minerba/detil/20260430-percepat-perizinan-ditjen-minerba-gelar-coaching-clinic-rkab",
        "timestamp": "2026-04-30 00:00:00"
    },
    {
        "title": "Mengawal Kekayaan Negara: Strategi Pengendalian dan Mitigasi Korupsi Sektor Minerba",
        "source": "https://www.minerba.esdm.go.id/berita/minerba/detil/20260428-mengawal-kekayaan-negara-strategi-pengendalian-dan-mitigasi-korupsi-sektor-minerba",
        "timestamp": "2026-04-28 00:00:00"
    },
    {
        "title": "Dirjen Minerba Lepas Delegasi Tim Garuda Mine Rescue ke Ajang IMRC 2026 di Zambia",
        "source": "https://www.minerba.esdm.go.id/berita/minerba/detil/20260421-dirjen-minerba-lepas-delegasi-tim-garuda-mine-rescue-ke-ajang-imrc-2026-di-zambia",
        "timestamp": "2026-04-21 00:00:00"
    },
    {
        "title": "Penguatan Ketahanan Energi Nasional: Strategi Minerba dan Kolaborasi Industri\u2013Perguruan Tinggi",
        "source": "https://www.minerba.esdm.go.id/berita/minerba/detil/20260416-penguatan-ketahanan-energi-nasional-strategi-minerba-dan-kolaborasi-industri-perguruan-tinggi",
        "timestamp": "2026-04-16 00:00:00"
    },
    {
        "title": "Kepmen ESDM 144/2026 Ditetapkan: Penguatan Tata Kelola Harga Patokan Mineral Logam dan Batubara",
        "source": "https://www.minerba.esdm.go.id/berita/minerba/detil/20260413-kepmen-esdm-144-2026-ditetapkan-penguatan-tata-kelola-harga-patokan-mineral-logam-dan-batubara",
        "timestamp": "2026-04-13 00:00:00"
    },
    {
        "title": "Bank Central Asia's margin falls in Q1 as wholesale competition weighs",
        "source": "https://asianbankingandfinance.net/lending-credit/news/bank-central-asias-margin-falls-in-q1-wholesale-competition-weighs",
        "timestamp": "2026-04-30 06:12:55"
    },
    {
        "title": "Bank Mandiri Q1 profit up 16.6% as Agrinas drives loan growth",
        "source": "https://asianbankingandfinance.net/retail-banking/news/bank-mandiri-q1-profit-166-agrinas-drives-loan-growth",
        "timestamp": "2026-04-28 06:12:56"
    },
    {
        "title": "Bank Mandiri says oil shock could lift bad loan ratio to 4%: report",
        "source": "https://asianbankingandfinance.net/retail-banking/news/bank-mandiri-says-oil-shock-could-lift-bad-loan-ratio-4-report",
        "timestamp": "2026-05-03 06:12:56"
    },
    {
        "title": "Indonesia card payments to reach $61.3b in 2026",
        "source": "https://asianbankingandfinance.net/cards-payments/in-focus/indonesia-card-payments-reach-613b-in-2026",
        "timestamp": "2026-05-03 06:12:56"
    },
    {
        "title": "CIMB Niaga launches two AI agents for bank staff",
        "source": "https://asianbankingandfinance.net/banking-technology/news/cimb-niaga-launches-two-ai-agents-bank-staff",
        "timestamp": "2026-05-03 06:12:56"
    },
    {
        "title": "Indonesia and South Korea link QR payments to bypass foreign exchange",
        "source": "https://asianbankingandfinance.net/cards-payments/news/indonesia-and-south-korea-link-qr-payments-bypass-foreign-exchange",
        "timestamp": "2026-05-03 06:12:56"
    },
    {
        "title": "Maybank Indonesia shifts to selective lending",
        "source": "https://asianbankingandfinance.net/exclusive/maybank-indonesia-shifts-selective-lending",
        "timestamp": "2026-05-03 06:12:56"
    },
    {
        "title": "Indonesian banks face limited hit from rising bond yields",
        "source": "https://asianbankingandfinance.net/retail-banking/in-focus/indonesian-banks-face-limited-hit-rising-bond-yields",
        "timestamp": "2026-05-03 06:12:56"
    },
    {
        "title": "BTN expands beyond mortgages into retail banking",
        "source": "https://asianbankingandfinance.net/exclusive/btn-expands-beyond-mortgages-retail-banking",
        "timestamp": "2026-05-03 06:12:56"
    },
    {
        "title": "Indonesian banks gain funding relief as deposits rise 16%",
        "source": "https://asianbankingandfinance.net/retail-banking/in-focus/indonesian-banks-gain-funding-relief-deposits-rise-16",
        "timestamp": "2026-05-03 06:12:56"
    },
    {
        "title": "Bank Central Asia\u2019s net profit rise 5.8% to $287.65m in Jan 2026",
        "source": "https://asianbankingandfinance.net/retail-banking/news/bank-central-asias-net-profit-rise-58-28765m-in-jan-2026",
        "timestamp": "2026-05-03 06:12:56"
    },
    {
        "title": "Indonesia\u2019s Islamic loans to grow 10% but banks capped at 8% market share",
        "source": "https://asianbankingandfinance.net/islamic-banking/in-focus/indonesias-islamic-loans-grow-10-banks-capped-8-market-share",
        "timestamp": "2026-05-03 06:12:56"
    },
    {
        "title": "BNI braces for NIM compression in 2026 on tighter H1 liquidity",
        "source": "https://asianbankingandfinance.net/retail-banking/news/bni-braces-nim-compression-in-2026-tighter-h1-liquidity",
        "timestamp": "2026-05-03 06:12:56"
    },
    {
        "title": "Indonesia loan demand stagnates as MSME and consumption slumps",
        "source": "https://asianbankingandfinance.net/retail-banking/in-focus/indonesia-loan-demand-stagnates-msme-and-consumption-slumps",
        "timestamp": "2026-05-03 06:12:56"
    },
    {
        "title": "Payroll drives rural Indonesia banking uptake as digital banks fail to sway users",
        "source": "https://asianbankingandfinance.net/retail-banking/in-focus/payroll-drives-rural-indonesia-banking-uptake-digital-banks-fail-sway-users",
        "timestamp": "2026-05-03 06:12:56"
    },
    {
        "title": "Human Sparsity Blockchain: A citizen-validated ledger for digital finance supervision",
        "source": "https://asianbankingandfinance.net/financial-technology/commentary/human-sparsity-blockchain-citizen-validated-ledger-digital-finance-supervision",
        "timestamp": "2026-05-03 06:12:56"
    },
    {
        "title": "Indonesia's Artajasa ties up with Ant International on cross-border payments",
        "source": "https://asianbankingandfinance.net/cards-payments/news/indonesias-artajasa-ties-ant-international-cross-border-payments",
        "timestamp": "2026-05-03 06:12:56"
    },
    {
        "title": "Merdeka Gold Completes Sale of 16 kg Gold from Pani Mine to Antam",
        "source": "https://indonesiaminer.com/news/detail/merdeka-gold-completes-sale-of-16-kg-gold-from-pani-mine-to-antam",
        "timestamp": "2026-03-16 08:08:00"
    },
    {
        "title": "Indonesia and Japan Agree on Cooperation for Critical Minerals and Nuclear Energy",
        "source": "https://indonesiaminer.com/news/detail/indonesia-and-japan-agree-on-cooperation-for-critical-minerals-and-nuclear-energy",
        "timestamp": "2026-03-15 08:35:00"
    },
    {
        "title": "The Ministry of Energy and Mineral Resources Endorses 300 Million Tons of Coal RKAB in 2026",
        "source": "https://indonesiaminer.com/news/detail/the-ministry-of-energy-and-mineral-resources-endorses-300-million-tons-of-coal-rkab-in-2026",
        "timestamp": "2026-03-13 08:10:00"
    },
    {
        "title": "Nickel Market Could Shift to Deficit Due to Indonesia Quota, Says Macquarie",
        "source": "https://indonesiaminer.com/news/detail/nickel-market-could-shift-to-deficit-due-to-indonesia-quota-says-macquarie",
        "timestamp": "2026-03-11 08:20:00"
    },
    {
        "title": "RMKE, Pendopo Energi Batubara Sign MoU to Develop Coal Logistics Infrastructure in S. Sumatra",
        "source": "https://indonesiaminer.com/news/detail/rmke-pendopo-energi-batubara-sign-mou-to-develop-coal-logistics-infrastructure-in-s-sumatra",
        "timestamp": "2026-03-11 08:01:00"
    },
    {
        "title": "Far East Gold Extends High-grade Gold Mineralisation at Sua Prospect Ahead of Resource Update",
        "source": "https://indonesiaminer.com/news/detail/far-east-gold-extends-high-grade-gold-mineralisation-at-sua-prospect-ahead-of-resource-update",
        "timestamp": "2026-03-10 22:41:00"
    },
    {
        "title": "Petrosea Posts 197% Surge in Net Profit for 2025",
        "source": "https://indonesiaminer.com/news/detail/petrosea-posts-197-surge-in-net-profit-for-2025",
        "timestamp": "2026-03-07 10:28:00"
    },
    {
        "title": "Vale\u2019s Sorowako Nickel Matte Production Unaffected by RKAB Quota Cuts",
        "source": "https://indonesiaminer.com/news/detail/vales-sorowako-nickel-matte-production-unaffected-by-rkab-quota-cuts",
        "timestamp": "2026-03-07 10:13:00"
    },
    {
        "title": "Building Integrated Smelters, MIND ID Aims to Reduce Indonesia\u2019s Aluminium Imports",
        "source": "https://indonesiaminer.com/news/detail/building-integrated-smelters-mind-id-aims-to-reduce-indonesias-aluminium-imports",
        "timestamp": "2026-03-06 10:05:00"
    },
    {
        "title": "Merdeka Copper Gold Partners with Aneka Tambang in 3-Ton Annual Gold Sales Agreement",
        "source": "https://indonesiaminer.com/news/detail/merdeka-copper-gold-partners-with-aneka-tambang-in-3-ton-annual-gold-sales-agreement",
        "timestamp": "2026-03-05 09:59:00"
    },
    {
        "title": "Indonesia Stock Exchange Sees 15 Firms Lined Up for IPOs",
        "body": "IDX lists 15 firms in IPO pipeline, mostly large-cap, spanning energy to tech as listings activity begins to pick up.",
        "source": "https://jakartaglobe.id/business/indonesia-stock-exchange-sees-15-firms-lined-up-for-ipos",
        "timestamp": "2026-05-03 04:13:07"
    },
    {
        "title": "Spirit Airlines to Shut Down After 34 Years, Ceases Operations Immediately",
        "body": "Spirit Airlines is shutting down after 34 years, canceling all flights immediately after failing to secure a government bailout.",
        "source": "https://jakartaglobe.id/business/spirit-airlines-to-shut-down-after-34-years-ceases-operations-immediately",
        "timestamp": "2026-05-02 10:13:07"
    },
    {
        "title": "GoTo, Grab Review Indonesia\u2019s New Rule Raising Driver Pay Share",
        "body": "GoTo and Grab review Indonesia\u2019s new rule raising driver pay to 92%, as firms assess impact on costs, pricing and industry sustainability.",
        "source": "https://jakartaglobe.id/business/goto-grab-review-indonesias-new-rule-raising-driver-pay-share",
        "timestamp": "2026-05-01 20:03:00"
    },
    {
        "title": "Danantara Responds to Claims of Buying Online Motor Taxi Shares",
        "body": "Danantara says it \"continually evaluates diverse market opportunities\" amid claims that the fund has bought ride-hailing apps's shares.",
        "source": "https://jakartaglobe.id/business/danantara-responds-to-claims-of-buying-online-motor-taxi-shares",
        "timestamp": "2026-05-01 17:40:00"
    },
    {
        "title": "Timah Profit Surges 1,184% as Output Jumps and Tin Prices Rally",
        "body": "Timah posts 1,184% profit jump in Q1 as output, sales and tin prices surge, beating targets and signaling continued growth momentum.",
        "source": "https://jakartaglobe.id/business/timah-profit-surges-1184-as-output-jumps-and-tin-prices-rally",
        "timestamp": "2026-05-01 17:34:00"
    },
    {
        "title": "ASEAN Agrees to Avoid \u2018Unnecessary\u2019 Trade Barriers as Iran Crisis Stings",
        "body": "ASEAN says any emergency measures must be temporary, and not create unnecessary barriers to trade as the group deals with the Iran crisis.",
        "source": "https://jakartaglobe.id/business/asean-agrees-to-avoid-unnecessary-trade-barriers-as-iran-crisis-stings",
        "timestamp": "2026-05-01 14:00:00"
    },
    {
        "title": "Indonesia Posts Rp 240 Trillion Budget Deficit in Q1 2026",
        "body": "Tax revenue remained the primary driver -- rising 20.7% -- but customs and excise revenue fell 12.6%.",
        "source": "https://jakartaglobe.id/business/indonesia-posts-rp-240-trillion-budget-deficit-in-q1-2026",
        "timestamp": "2026-05-01 13:25:00"
    },
    {
        "title": "Indonesia Caps Ride-Hailing Commissions at 8% to Protect Drivers",
        "body": "Indonesia caps ride-hailing commissions at 8% and expands social protections, aiming to boost welfare for over 4 million drivers",
        "source": "https://jakartaglobe.id/business/indonesia-caps-ridehailing-commissions-at-8-to-protect-drivers",
        "timestamp": "2026-05-01 12:23:00"
    },
    {
        "title": "Barito Renewables Posts $53 Million Q1 Profit on Strong Geothermal Output",
        "body": "New projects are expected to lift the company\u2019s total geothermal capacity to more than 1,000 MW by the end of 2026.",
        "source": "https://jakartaglobe.id/business/barito-renewables-posts-53-million-q1-profit-on-strong-geothermal-output",
        "timestamp": "2026-04-30 23:11:00"
    },
    {
        "title": "Indonesia Eases Local Content Certification for Small Industries",
        "body": "Indonesia makes local content certification free and simpler for small industries to boost access to government procurement.",
        "source": "https://jakartaglobe.id/business/indonesia-eases-local-content-certification-for-small-industries",
        "timestamp": "2026-04-30 23:10:00"
    },
    {
        "title": "Gudang Garam Reports Highest Quarterly Profit Since 2023",
        "body": "The result already accounts for roughly half of the company\u2019s projected full-year net profit.",
        "source": "https://jakartaglobe.id/business/gudang-garam-reports-highest-quarterly-profit-since-2023",
        "timestamp": "2026-04-30 23:05:00"
    },
    {
        "title": "Palm Oil Seen Up 8% in 2026 as Supply Caps Gains, World Bank Says",
        "body": "World Bank sees palm oil rising 8% in 2026, with supply growth and higher costs capping further gains.",
        "source": "https://jakartaglobe.id/business/palm-oil-seen-up-8-in-2026-as-supply-caps-gains-world-bank-says",
        "timestamp": "2026-04-30 22:26:00"
    },
    {
        "title": "Bukit Asam Q1 Profit More Than Doubles Despite Slight Revenue Dip",
        "body": "The profit increase was driven by stronger global coal prices, which supported margins despite softer top-line performance.",
        "source": "https://jakartaglobe.id/business/bukit-asam-q1-profit-more-than-doubles-despite-slight-revenue-dip",
        "timestamp": "2026-04-30 22:19:00"
    },
    {
        "title": "Unilever Indonesia Q1 Net Profit Rises 14% to Rp1.25 Trillion",
        "body": "The improved performance extends a recovery trend in both revenue and earnings that has been underway since the second half of 2025.",
        "source": "https://jakartaglobe.id/business/unilever-indonesia-q1-net-profit-rises-14-to-rp125-trillion",
        "timestamp": "2026-04-30 21:59:00"
    },
    {
        "title": "Rupiah Sinks to All-Time Low, Economist Warns of Overshooting",
        "body": "Rupiah falls to Rp 17,346 as Fed holds rates, with economists warning of overshooting and urging Bank Indonesia to act.",
        "source": "https://jakartaglobe.id/business/rupiah-sinks-to-alltime-low-economist-warns-of-overshooting",
        "timestamp": "2026-04-30 21:36:00"
    },
    {
        "title": "Amman Mineral Swings to $163 Million Q1 Profit",
        "body": "The company obtained a temporary permit on Oct. 31, 2025, to export concentrate for six months through April 30, 2026.",
        "source": "https://jakartaglobe.id/business/amman-mineral-swings-to-163-million-q1-profit",
        "timestamp": "2026-04-30 21:35:00"
    },
    {
        "title": "CIMB Niaga Q1 Net Profit Slips 2.2% to Rp1.76 Trillion",
        "body": "Financial transactions conducted via the OCTO mobile banking application rose 29% in the first quarter.",
        "source": "https://jakartaglobe.id/business/cimb-niaga-q1-net-profit-slips-22-to-rp176-trillion",
        "timestamp": "2026-04-30 20:07:00"
    },
    {
        "title": "Tax Office Assures Data Security as Coretax System Under Scrutiny",
        "body": "Indonesia\u2019s tax office says taxpayer data is secure and regularly audited, as concerns persist over its Coretax digital system.",
        "source": "https://jakartaglobe.id/business/tax-office-assures-data-security-as-coretax-system-under-scrutiny",
        "timestamp": "2026-04-30 17:11:00"
    },
    {
        "title": "Rupiah Drops to Rp 17,353 as Oil Risks, Fed Jitters Weigh",
        "body": "Rupiah falls to Rp 17,353 as US-Iran tensions and Fed leadership uncertainty drive demand for the dollar.",
        "source": "https://jakartaglobe.id/business/rupiah-drops-to-rp-17353-as-oil-risks-fed-jitters-weigh",
        "timestamp": "2026-04-30 16:36:00"
    },
    {
        "title": "JCI Falls 2% on Oil Surge Fears, Weak Rupiah and Fed Policy Uncertainty",
        "body": "JCI drops 2% as US\u2013Iran tensions, fuel price hikes, and rupiah weakness trigger broad sell-off across sectors.",
        "source": "https://jakartaglobe.id/business/jci-falls-2-on-oil-surge-fears-weak-rupiah-and-fed-policy-uncertainty",
        "timestamp": "2026-04-30 16:17:00"
    },
    {
        "title": "TOBA kantongi pertumbuhan pendapatan 20,5 persen pada kuartal I 2026",
        "source": "https://www.antaranews.com/berita/5550937/toba-kantongi-pertumbuhan-pendapatan-205-persen-pada-kuartal-i-2026",
        "timestamp": "2026-05-02 09:48:00"
    },
    {
        "title": "PT Timah cetak laba bersih Rp1,5 triliun di kuartal I 2026",
        "source": "https://www.antaranews.com/berita/5550908/pt-timah-cetak-laba-bersih-rp15-triliun-di-kuartal-i-2026",
        "timestamp": "2026-05-02 08:26:00"
    },
    {
        "title": "IHSG melemah dipicu kombinasi \"risk off\" global dan tekanan domestik",
        "source": "https://www.antaranews.com/berita/5548917/ihsg-melemah-dipicu-kombinasi-risk-off-global-dan-tekanan-domestik",
        "timestamp": "2026-04-30 17:32:00"
    },
    {
        "title": "IHSG berpotensi melemah dipicu \"profit taking\" jelang libur panjang",
        "source": "https://www.antaranews.com/berita/5548264/ihsg-berpotensi-melemah-dipicu-profit-taking-jelang-libur-panjang",
        "timestamp": "2026-04-30 09:58:00"
    },
    {
        "title": "IHSG Kamis dibuka menguat 2,03 poin",
        "source": "https://www.antaranews.com/berita/5548208/ihsg-kamis-dibuka-menguat-203-poin",
        "timestamp": "2026-04-30 09:09:00"
    },
    {
        "title": "BCA mulai realisasikan aksi \"buyback\" saham",
        "source": "https://www.antaranews.com/berita/5547400/bca-mulai-realisasikan-aksi-buyback-saham",
        "timestamp": "2026-04-29 17:01:00"
    },
    {
        "title": "IHSG menguat, pasar cermati arah moneter global di tengah konflik",
        "source": "https://www.antaranews.com/berita/5546771/ihsg-menguat-pasar-cermati-arah-moneter-global-di-tengah-konflik",
        "timestamp": "2026-04-29 10:15:00"
    },
    {
        "title": "IHSG Rabu dibuka menguat 24,22 poin",
        "source": "https://www.antaranews.com/berita/5546695/ihsg-rabu-dibuka-menguat-2422-poin",
        "timestamp": "2026-04-29 09:17:00"
    },
    {
        "title": "IdScore: Industri kredit nasional solid di tengah tekanan geopolitik",
        "source": "https://www.antaranews.com/berita/5546048/idscore-industri-kredit-nasional-solid-di-tengah-tekanan-geopolitik",
        "timestamp": "2026-04-28 19:29:00"
    },
    {
        "title": "IHSG ditutup melemah, terbebani ketidakpastian penyelesaian AS-Iran",
        "source": "https://www.antaranews.com/berita/5545928/ihsg-ditutup-melemah-terbebani-ketidakpastian-penyelesaian-as-iran",
        "timestamp": "2026-04-28 18:03:00"
    },
    {
        "title": "IHSG berpotensi volatil di tengah \"wait and see\" pertemuan The Fed",
        "source": "https://www.antaranews.com/berita/5545073/ihsg-berpotensi-volatil-di-tengah-wait-and-see-pertemuan-the-fed",
        "timestamp": "2026-04-28 10:02:00"
    },
    {
        "title": "IHSG Selasa dibuka menguat 21,95 poin",
        "source": "https://www.antaranews.com/berita/5545008/ihsg-selasa-dibuka-menguat-2195-poin",
        "timestamp": "2026-04-28 09:12:00"
    },
    {
        "title": "OJK target umumkan direksi BEI terpilih paling lambat pada 22 Juni",
        "source": "https://www.antaranews.com/berita/5544464/ojk-target-umumkan-direksi-bei-terpilih-paling-lambat-pada-22-juni",
        "timestamp": "2026-04-27 19:53:00"
    },
    {
        "title": "Menkeu Purbaya pertimbangkan insentif untuk pasar modal",
        "source": "https://www.antaranews.com/berita/5544279/menkeu-purbaya-pertimbangkan-insentif-untuk-pasar-modal",
        "timestamp": "2026-04-27 17:41:00"
    },
    {
        "title": "OJK sebut demutualisasi bursa masuk dalam materi revisi UU P2SK",
        "source": "https://www.antaranews.com/berita/5544260/ojk-sebut-demutualisasi-bursa-masuk-dalam-materi-revisi-uu-p2sk",
        "timestamp": "2026-04-27 17:28:00"
    },
    {
        "title": "IHSG Senin sore ditutup melemah ke level 7.106,52",
        "source": "https://www.antaranews.com/berita/5544229/ihsg-senin-sore-ditutup-melemah-ke-level-710652",
        "timestamp": "2026-04-27 17:13:00"
    },
    {
        "title": "IHSG berpotensi melemah di tengah tekanan rupiah dan sentimen global",
        "source": "https://www.antaranews.com/berita/5543485/ihsg-berpotensi-melemah-di-tengah-tekanan-rupiah-dan-sentimen-global",
        "timestamp": "2026-04-27 09:42:00"
    },
    {
        "title": "IHSG Senin pagi dibuka menguat 29,02 poin",
        "source": "https://www.antaranews.com/berita/5543449/ihsg-senin-pagi-dibuka-menguat-2902-poin",
        "timestamp": "2026-04-27 09:09:00"
    },
    {
        "title": "Pasar cermati arah moneter global, IHSG diproyeksi mendatar pekan ini",
        "source": "https://www.antaranews.com/berita/5543356/pasar-cermati-arah-moneter-global-ihsg-diproyeksi-mendatar-pekan-ini",
        "timestamp": "2026-04-27 05:56:00"
    },
    {
        "title": "Purbaya yakin IHSG tetap mampu tembus 10.000 pada tahun ini",
        "source": "https://www.antaranews.com/berita/5541408/purbaya-yakin-ihsg-tetap-mampu-tembus-10000-pada-tahun-ini",
        "timestamp": "2026-04-24 20:22:00"
    },
    {
        "title": "MyRepublic launches 5G wireless broadband in Indonesia",
        "source": "https://asiantelecom.com/exclusive/myrepublic-launches-5g-wireless-broadband-in-indonesia",
        "timestamp": "2026-03-08 20:37:01"
    },
    {
        "title": "MyRepublic launches 5G wireless broadband in Indonesia",
        "source": "https://asiantelecom.com/exclusive/myrepublic-launches-5g-wireless-broadband-in-indonesia",
        "timestamp": "2026-03-08 20:37:01"
    },
    {
        "title": "PT Dayamitra Telekomunikasi Tbk redefines sustainable infrastructure at Asian Telecom  Awards 2026",
        "source": "https://asiantelecom.com/co-written-partner/event-news/pt-dayamitra-telekomunikasi-tbk-redefines-sustainable-infrastructure-asian-telecom-awards-2026",
        "timestamp": "2026-03-03 10:40:14"
    },
    {
        "title": "MyRepublic Indonesia recognised for deployment speed and broadband leadership at Asian Telecom Awards 2026",
        "source": "https://asiantelecom.com/co-written-partner/event-news/myrepublic-indonesia-recognised-deployment-speed-and-broadband-leadership-asian-telecom-awards-2026",
        "timestamp": "2026-02-25 10:53:09"
    },
    {
        "title": "PT. Telkomsel wins two awards at Asian Telecom Awards 2026",
        "source": "https://asiantelecom.com/co-written-partner/event-news/pt-telkomsel-wins-two-awards-asian-telecom-awards-2026",
        "timestamp": "2026-02-25 10:49:52"
    },
    {
        "title": "Telin recognised for cybersecurity and submarine network leadership at Asian Telecom Awards 2026",
        "source": "https://asiantelecom.com/co-written-partner/event-news/telin-recognised-cybersecurity-and-submarine-network-leadership-asian-telecom-awards-2026",
        "timestamp": "2026-02-25 10:44:40"
    },
    {
        "title": "Indosat Ooredoo Hutchison (IOH) wins at Asian Telecom Awards 2026",
        "source": "https://asiantelecom.com/co-written-partner/event-news/indosat-ooredoo-hutchison-ioh-wins-asian-telecom-awards-2026",
        "timestamp": "2026-02-25 10:39:45"
    },
    {
        "title": "Telkomsel expands business messaging beyond SMS",
        "source": "https://asiantelecom.com/exclusive/telkomsel-expands-business-messaging-beyond-sms",
        "timestamp": "2026-01-20 18:16:51"
    },
    {
        "title": "Indonesia urged to focus on digital investment",
        "source": "https://asiantelecom.com/news/indonesia-urged-focus-digital-investment",
        "timestamp": "2025-12-22 06:00:00"
    },
    {
        "title": "Indonesia telecom sales to grow by 3.7% CAGR through 2029",
        "source": "https://asiantelecom.com/news/indonesia-telecom-sales-grow-37-cagr-through-2029",
        "timestamp": "2025-12-12 14:22:47"
    },
    {
        "title": "Indosat flags 290 million spam calls in 3 months",
        "source": "https://asiantelecom.com/exclusive/indosat-flags-290-million-spam-calls-in-3-months",
        "timestamp": "2025-11-17 13:32:06"
    },
    {
        "title": "Indonesia, Timor-Leste eye connectivity collaboration",
        "source": "https://asiantelecom.com/news/indonesia-timor-leste-eye-connectivity-collaboration",
        "timestamp": "2025-11-03 05:01:17"
    },
    {
        "title": "Indonesia telcos set for ARPU rebound as pricing discipline strengthens",
        "source": "https://asiantelecom.com/news/indonesia-telcos-set-arpu-rebound-pricing-discipline-strengthens",
        "timestamp": "2025-10-07 08:17:05"
    },
    {
        "title": "Fluid licence on affiliated companies: An explorative strategy to consolidate Indonesia\u2019s telecom industry",
        "source": "https://asiantelecom.com/commentary/fluid-licence-affiliated-companies-explorative-strategy-consolidate-indonesias-telecom-industry",
        "timestamp": "2025-09-30 14:20:27"
    },
    {
        "title": "Japan to back telcos looking to set up infrastructure in Indonesia",
        "source": "https://asiantelecom.com/news/japan-back-telcos-looking-set-infrastructure-in-indonesia",
        "timestamp": "2025-08-19 14:31:37"
    },
    {
        "title": "Business partnership as TKDN services: Unlocking Indonesia\u2019s digital future",
        "source": "https://asiantelecom.com/commentary/business-partnership-tkdn-services-unlocking-indonesias-digital-future",
        "timestamp": "2025-05-05 12:55:00"
    },
    {
        "title": "PT Eka Mas Republik wins two accolades at Asian Telecom Awards 2025",
        "source": "https://asiantelecom.com/co-written-partner/event-news/pt-eka-mas-republik-wins-two-accolades-asian-telecom-awards-2025",
        "timestamp": "2025-03-13 09:22:54"
    },
    {
        "title": "Indonesia adopts faster Wi-Fi to drive growth",
        "source": "https://asiantelecom.com/exclusive/indonesia-adopts-faster-wi-fi-drive-growth",
        "timestamp": "2025-02-27 21:03:34"
    },
    {
        "title": "Trump warns Iran blockade could last months, sending oil soaring",
        "source": "https://www.thejakartapost.com/business/2026/04/30/trump-warns-iran-blockade-could-last-months-sending-oil-soaring.html?utm_source=(direct)&utm_medium=channel_markets",
        "timestamp": "2026-04-30 00:00:00"
    },
    {
        "title": "Crude extends gains as Trump considers latest Iran proposal",
        "source": "https://www.thejakartapost.com/business/2026/04/28/crude-extends-gains-as-trump-considers-latest-iran-proposal.html?utm_source=(direct)&utm_medium=channel_markets",
        "timestamp": "2026-04-28 00:00:00"
    },
    {
        "title": "Chips carry stocks higher; oil jumps on stalled peace talks",
        "source": "https://www.thejakartapost.com/business/2026/04/27/chips-carry-stocks-higher-oil-jumps-on-stalled-peace-talks.html?utm_source=(direct)&utm_medium=channel_markets",
        "timestamp": "2026-04-27 00:00:00"
    },
    {
        "title": "Asian shares pull back from record highs as oil gains on Iran risk",
        "source": "https://www.thejakartapost.com/business/2026/04/23/asian-shares-pull-back-from-record-highs-as-oil-gains-on-iran-risk.html?utm_source=(direct)&utm_medium=channel_markets",
        "timestamp": "2026-04-23 00:00:00"
    },
    {
        "title": "India to import record 2.5m tons of urea at nearly double price",
        "source": "https://www.thejakartapost.com/business/2026/04/23/india-to-import-record-25m-tons-of-urea-at-nearly-double-price.html?utm_source=(direct)&utm_medium=channel_markets",
        "timestamp": "2026-04-23 00:00:00"
    },
    {
        "title": "Malaysia offers rare earths alternative to China",
        "source": "https://www.thejakartapost.com/business/2026/04/22/malaysia-offers-rare-earths-alternative-to-china.html?utm_source=(direct)&utm_medium=channel_markets",
        "timestamp": "2026-04-22 00:00:00"
    },
    {
        "title": "Oil, stocks fall as traders weigh outlook after Trump extends truce",
        "source": "https://www.thejakartapost.com/business/2026/04/22/oil-stocks-fall-as-traders-weigh-outlook-after-trump-extends-truce.html?utm_source=(direct)&utm_medium=channel_markets",
        "timestamp": "2026-04-22 00:00:00"
    },
    {
        "title": "Oil prices dip, stocks rise on lingering Iran peace hopes",
        "source": "https://www.thejakartapost.com/business/2026/04/21/oil-prices-dip-stocks-rise-on-lingering-iran-peace-hopes.html?utm_source=(direct)&utm_medium=channel_markets",
        "timestamp": "2026-04-21 00:00:00"
    },
    {
        "title": "Oil jumps, stocks wobble as Mideast ceasefire hangs in the balance",
        "source": "https://www.thejakartapost.com/business/2026/04/20/oil-jumps-stocks-wobble-as-mideast-ceasefire-hangs-in-the-balance.html?utm_source=(direct)&utm_medium=channel_markets",
        "timestamp": "2026-04-20 00:00:00"
    },
    {
        "title": "Iran says final deal still far off as Hormuz Strait shuttered",
        "source": "https://www.thejakartapost.com/business/2026/04/19/iran-says-final-deal-still-far-off-as-hormuz-strait-shuttered.html?utm_source=(direct)&utm_medium=channel_markets",
        "timestamp": "2026-04-19 00:00:00"
    },
    {
        "title": "Sanctioned tanker turns back to Strait of Hormuz, day after Gulf exit",
        "source": "https://www.thejakartapost.com/business/2026/04/15/sanctioned-tanker-turns-back-to-strait-of-hormuz-day-after-gulf-exit.html?utm_source=(direct)&utm_medium=channel_markets",
        "timestamp": "2026-04-15 00:00:00"
    },
    {
        "title": "Asian stocks rally, crude drops on lingering hope for a peace deal",
        "source": "https://www.thejakartapost.com/business/2026/04/14/asian-stocks-rally-crude-drops-on-lingering-hope-for-a-peace-deal.html?utm_source=(direct)&utm_medium=channel_markets",
        "timestamp": "2026-04-14 00:00:00"
    },
    {
        "title": "Oil surges, stocks fall as Trump says to blockade Strait of Hormuz",
        "source": "https://www.thejakartapost.com/business/2026/04/13/oil-surges-stocks-fall-as-trump-says-to-blockade-strait-of-hormuz.html?utm_source=(direct)&utm_medium=channel_markets",
        "timestamp": "2026-04-13 00:00:00"
    },
    {
        "title": "US oil benchmark jumps 8%, surpasses $100 after failed US-Iran talks",
        "source": "https://www.thejakartapost.com/business/2026/04/13/us-oil-benchmark-jumps-8-surpasses-100-after-failed-us-iran-talks.html?utm_source=(direct)&utm_medium=channel_markets",
        "timestamp": "2026-04-13 00:00:00"
    },
    {
        "title": "Oil prices jump, stocks drop on Mideast ceasefire doubts",
        "source": "https://www.thejakartapost.com/business/2026/04/09/oil-prices-jump-stocks-drop-on-mideast-ceasefire-doubts.html?utm_source=(direct)&utm_medium=channel_markets",
        "timestamp": "2026-04-09 00:00:00"
    },
    {
        "title": "Crude rises, stocks fall on fears over nascent Iran ceasefire",
        "source": "https://www.thejakartapost.com/business/2026/04/09/crude-rises-stocks-fall-on-fears-over-nascent-iran-ceasefire.html?utm_source=(direct)&utm_medium=channel_markets",
        "timestamp": "2026-04-09 00:00:00"
    },
    {
        "title": "Oil plunges, Asia stocks soar after US, Iran ceasefire",
        "source": "https://www.thejakartapost.com/business/2026/04/08/oil-plunges-asia-stocks-soar-after-us-iran-ceasefire.html?utm_source=(direct)&utm_medium=channel_markets",
        "timestamp": "2026-04-08 00:00:00"
    },
    {
        "title": "Stocks struggle, oil jumps as Trump's Iran deadline looms",
        "source": "https://www.thejakartapost.com/business/2026/04/07/stocks-struggle-oil-jumps-as-trumps-iran-deadline-looms.html?utm_source=(direct)&utm_medium=channel_markets",
        "timestamp": "2026-04-07 00:00:00"
    },
    {
        "title": "US crude benchmark opens over $113, Brent above $110",
        "source": "https://www.thejakartapost.com/business/2026/04/06/us-crude-benchmark-opens-over-113-brent-above-110.html?utm_source=(direct)&utm_medium=channel_markets",
        "timestamp": "2026-04-06 00:00:00"
    },
    {
        "title": "Indonesia says stock market reform drive completed after Feb's selloffs",
        "source": "https://www.thejakartapost.com/business/2026/04/03/indonesia-says-stock-market-reform-drive-completed-after-febs-selloffs.html?utm_source=(direct)&utm_medium=channel_markets",
        "timestamp": "2026-04-03 00:00:00"
    },
    {
        "title": "India's March palm oil imports fall to 3-month low as prices surge",
        "source": "https://www.thejakartapost.com/business/2026/04/02/indias-march-palm-oil-imports-fall-to-3-month-low-as-prices-surge.html?utm_source=(direct)&utm_medium=channel_markets",
        "timestamp": "2026-04-02 00:00:00"
    },
    {
        "title": "Oil rallies, stocks tumble as Trump says US to hammer Iran further",
        "source": "https://www.thejakartapost.com/business/2026/04/02/oil-rallies-stocks-tumble-as-trump-says-us-to-hammer-iran-further.html?utm_source=(direct)&utm_medium=channel_markets",
        "timestamp": "2026-04-02 00:00:00"
    },
    {
        "title": "Asian stocks rally as Trump says war to end 'very soon'",
        "source": "https://www.thejakartapost.com/business/2026/04/01/asian-stocks-rally-as-trump-says-war-to-end-very-soon.html?utm_source=(direct)&utm_medium=channel_markets",
        "timestamp": "2026-04-01 00:00:00"
    },
    {
        "title": "Dollar surges in Asia as war's safe-haven shelter",
        "source": "https://www.thejakartapost.com/business/2026/03/31/dollar-surges-in-asia-as-wars-safe-haven-shelter.html?utm_source=(direct)&utm_medium=channel_markets",
        "timestamp": "2026-03-31 00:00:00"
    },
    {
        "title": "Japan steps up yen intervention threats, signals rate-hike chance",
        "source": "https://www.thejakartapost.com/business/2026/03/30/japan-steps-up-yen-intervention-threats-signals-rate-hike-chance.html?utm_source=(direct)&utm_medium=channel_markets",
        "timestamp": "2026-03-30 00:00:00"
    },
    {
        "title": "Fuel-thirsty Asian countries line up for Russian oil",
        "source": "https://www.thejakartapost.com/business/2026/03/27/fuel-thirsty-asian-countries-line-up-for-russian-oil.html?utm_source=(direct)&utm_medium=channel_markets",
        "timestamp": "2026-03-27 00:00:00"
    },
    {
        "title": "Menanti Data Manufaktur, Begini Proyeksi Rupiah untuk Senin, (4/5)",
        "source": "https://investasi.kontan.co.id/news/menanti-data-manufaktur-begini-proyeksi-rupiah-untuk-senin-45",
        "timestamp": "2026-05-03 00:00:00"
    },
    {
        "title": "Alamtri Resources (ADRO) Raih Pendapatan US$ 470,91 Juta pada Kuartal I-2026",
        "source": "https://investasi.kontan.co.id/news/alamtri-resources-adro-raih-pendapatan-us-47091-juta-pada-kuartal-i-2026",
        "timestamp": "2026-05-03 00:00:00"
    },
    {
        "title": "Lelang Spektrum 700 MHz dan 2,6 GHz Dimulai, Cek Rekomendasi Saham Telekomunikasi",
        "source": "https://investasi.kontan.co.id/news/lelang-spektrum-700-mhz-dan-26-ghz-dimulai-cek-rekomendasi-saham-telekomunikasi",
        "timestamp": "2026-05-03 00:00:00"
    },
    {
        "title": "IHSG Berpotensi Rawan Terkoreksi pada Senin (4/5/2026), Ini Penyebabnya",
        "source": "https://investasi.kontan.co.id/news/ihsg-rawan-terkoreksi-pada-senin-45-esok-ini-penyebabnya",
        "timestamp": "2026-05-03 00:00:00"
    },
    {
        "title": "Bitcoin Masih Volatil, Begini Prediksi Arah dan Level Kunci Harga",
        "source": "https://investasi.kontan.co.id/news/bitcoin-masih-volatil-begini-prediksi-arah-dan-level-kunci-harga",
        "timestamp": "2026-05-03 00:00:00"
    },
    {
        "title": "Harga Minyak Masih Berpotensi Tinggi, Investor Disarankan Tunggu Koreksi",
        "source": "https://investasi.kontan.co.id/news/harga-minyak-masih-berpotensi-tinggi-investor-disarankan-tunggu-koreksi",
        "timestamp": "2026-05-03 00:00:00"
    },
    {
        "title": "Kripto Bisa Jadi Bagian Aset Sitaan Negara, Ini Dampaknya",
        "source": "https://investasi.kontan.co.id/news/kripto-bisa-jadi-bagian-aset-sitaan-negara-ini-dampaknya",
        "timestamp": "2026-05-03 00:00:00"
    },
    {
        "title": "Daftar Harga Emas Antam Hari Ini (3/5) Tidak Berubah di Level Rp 2.796.000 Per Gram",
        "source": "https://investasi.kontan.co.id/news/daftar-harga-emas-antam-hari-ini-35-tidak-berubah-di-level-rp-2796000-per-gram",
        "timestamp": "2026-05-03 00:00:00"
    },
    {
        "title": "Kinerja Japfa Comfeed (JPFA) Dibayangi Tekanan Biaya Pakan, Cek Rekomendasi Analis",
        "source": "https://investasi.kontan.co.id/news/kinerja-japfa-comfeed-jpfa-dibayangi-tekanan-biaya-pakan-cek-rekomendasi-analis",
        "timestamp": "2026-05-03 00:00:00"
    },
    {
        "title": "Laba INDF Naik 9% Jadi Rp 2,92 Triliun Kuartal I-2026, Ini Penjelasan Anthoni Salim",
        "source": "https://investasi.kontan.co.id/news/laba-indf-naik-9-jadi-rp-292-triliun-kuartal-i-2026-ini-penjelasan-anthoni-salim",
        "timestamp": "2026-05-03 00:00:00"
    },
    {
        "title": "Laba PTBA Melonjak Meski Penjualan Melemah di Kuartal I, Ini Penjelasan Manajemen",
        "source": "https://investasi.kontan.co.id/news/laba-ptba-melonjak-meski-penjualan-melemah-di-kuartal-i-ini-penjelasan-manajemen",
        "timestamp": "2026-05-03 00:00:00"
    },
    {
        "title": "LABA Terus Jualan Saham KRYA, Nilainya Tembus Rp6,63M di April 2026",
        "source": "https://emitennews.com/news/laba-terus-jualan-saham-krya-nilainya-tembus-rp663m-di-april-2026",
        "timestamp": "2026-05-03 00:00:00"
    },
    {
        "title": "Penjualan CLEO Meningkat 15,8 Persen Q1-2026, Tiga Pabrik Baru Dikebut",
        "source": "https://emitennews.com/news/penjualan-cleo-meningkat-158-persen-q1-2026-tiga-pabrik-baru-dikebut",
        "timestamp": "2026-05-03 00:00:00"
    },
    {
        "title": "Kinerja Chitose (CINT) Tumbuh di Q1-2026, Target Segini di Akhir Tahun",
        "source": "https://emitennews.com/news/kinerja-chitose-cint-tumbuh-di-q1-2026-target-segini-di-akhir-tahun",
        "timestamp": "2026-05-03 00:00:00"
    },
    {
        "title": "Turnaround ICON dari Rugi Beruntun Jadi Laba Rp5,87 Miliar di 2025",
        "source": "https://emitennews.com/news/turnaround-icon-dari-rugi-beruntun-jadi-laba-rp587-miliar-di-2025",
        "timestamp": "2026-05-03 00:00:00"
    },
    {
        "title": "GOTO Respons Perpres Ojol, Danantara Bakal Jadi Pemegang Saham?",
        "source": "https://emitennews.com/news/goto-respons-perpres-ojol-danantara-bakal-jadi-pemegang-saham",
        "timestamp": "2026-05-03 00:00:00"
    },
    {
        "title": "Pendapatan Tertekan, Laba PTBA Justru Mengganda 104,81 Persen!",
        "source": "https://emitennews.com/news/pendapatan-tertekan-laba-ptba-justru-mengganda-10481-persen",
        "timestamp": "2026-05-03 00:00:00"
    },
    {
        "title": "Celebes Mining Cabut dari HOPE, Divestasi 13,87 Persen Saham Rp67,38M",
        "source": "https://emitennews.com/news/celebes-mining-cabut-dari-hope-divestasi-1387-persen-saham-rp6738m",
        "timestamp": "2026-05-03 00:00:00"
    },
    {
        "title": "Penjualan Seragam Melesat 209 Persen, BELL Untung Dua Digit di Q1 2026",
        "source": "https://emitennews.com/news/penjualan-seragam-melesat-209-persen-bell-untung-dua-digit-di-q1-2026",
        "timestamp": "2026-05-03 00:00:00"
    },
    {
        "title": "TINS Tabulasi Laba Rp1,5 Triliun, Melesat 1.183 Persen Kuartal I 2026",
        "source": "https://emitennews.com/news/tins-tabulasi-laba-rp15-triliun-melesat-1183-persen-kuartal-i-2026",
        "timestamp": "2026-05-02 00:00:00"
    },
    {
        "title": "TEKANAN PASAR ASET KRIPTO PENGARUHI KINERJA COIN DI KUARTAL I-2026 \n",
        "timestamp": "2026-04-30 02:24:52",
        "source": "https://bcasekuritas.co.id/en/latest-news/news/tekanan-pasar-aset-kripto-pengaruhi-kinerja-coin-di-kuartal-i-2026"
    },
    {
        "title": "IHSG SESI II DITUTUP MELEMAH 144 POIN DI LEVEL 6.956",
        "timestamp": "2026-04-30 02:20:35",
        "source": "https://bcasekuritas.co.id/en/latest-news/news/ihsg-sesi-ii-ditutup-melemah-144-poin-di-level-6956"
    },
    {
        "title": "OTORITAS IKN BANTU KEMANDIRAN EKONOMI MASYARAKAT LOKAL",
        "timestamp": "2026-04-30 02:14:17",
        "source": "https://bcasekuritas.co.id/en/latest-news/news/otoritas-ikn-bantu-kemandiran-ekonomi-masyarakat-lokal"
    },
    {
        "title": "PRODUKSI CPO SAWIT SUMBERMAS SARANA (SSMS) NAIK 14,23% DI SEPANJANG 2025",
        "timestamp": "2026-04-30 02:11:55",
        "source": "https://bcasekuritas.co.id/en/latest-news/news/produksi-cpo-sawit-sumbermas-sarana-ssms-naik-1423-di-sepanjang-2025"
    },
    {
        "title": "PRESIDEN PRABOWO: HILIRISASI HARUS BERBASIS TEKNOLOGI TERBAIK",
        "timestamp": "2026-04-30 02:09:23",
        "source": "https://bcasekuritas.co.id/en/latest-news/news/presiden-prabowo-hilirisasi-harus-berbasis-teknologi-terbaik"
    },
    {
        "title": "OTORITA IKN BANTU KAPASITAS DAN KEMANDIRIAN EKONOMI MASYARAKAT",
        "timestamp": "2026-04-30 02:07:01",
        "source": "https://bcasekuritas.co.id/en/latest-news/news/otorita-ikn-bantu-kapasitas-dan-kemandirian-ekonomi-masyarakat"
    }
]