{
  "real-estate-development": "properties-real-estate",
  "oil-gas-operations-services": "energy",
  "healthcare-facilities-services": "healthcare",
  "real-estate-diversified": "properties-real-estate",
  "retail": "consumer-cyclical",
  "real-estate-services": "properties-real-estate",
  "building-materials": "basic-materials",
  "reit-specialty-healthcare": "reit",
  "business-employment-services": "industrials",
  "food-beverage-production": "consumer-defensive",
  "reit-diversified": "reit",
  "medical-devices-supplies": "healthcare",
  "engineering-construction-building-products": "industrials",
  "chemicals": "basic-materials",
  "asset-management-investment": "financial-services",
  "aerospace-defense": "industrials",
  "pharmaceuticals-research": "healthcare",
  "conglomerates-holdings": "industrials",
  "reit-retail": "reit",
  "communication-instruments": "technology",
  "semiconductors-equipment": "technology",
  "software-it-services": "technology",
  "automotive": "consumer-cyclical",
  "furnishings-fixtures-appliances": "consumer-cyclical",
  "reit-industrial": "reit",
  "luxury-goods": "consumer-cyclical",
  "restaurants-food-retail": "consumer-cyclical",
  "industrial-machinery-parts": "industrials",
  "reit-office": "reit",
  "hotels-resorts-leisure": "consumer-cyclical",
  "banks-credit-services": "financial-services",
  "transportation-logistics": "industrials",
  "industrial-distribution": "industrials",
  "oil-gas-coal": "energy",
  "rental-leasing-security-services": "industrials",
  "hardware-electronics": "technology",
  "packaging-containers": "consumer-cyclical",
  "paper-forest-products": "basic-materials",
  "insurance": "financial-services",
  "telecommunication": "infrastructures",
  "media-entertainment": "communication-services",
  "metals-mining": "basic-materials",
  "food-beverage-retail-production": "consumer-non-cyclicals",
  "personal-services": "consumer-cyclical",
  "telecom-services": "communication-services",
  "utilities-regulated": "utilities",
  "education-training-services": "consumer-defensive",
  "utilities-independent-diversified": "utilities",
  "heavy-construction-transport-infrastructure": "infrastructures",
  "food-distribution": "consumer-defensive",
  "waste-management-pollution-control": "industrials",
  "other-real-estate-operations": "properties-real-estate",
  "apparel-accessories": "consumer-cyclical",
  "financial-data-shell-companies": "financial-services",
  "utilities-renewable": "utilities"
}