[
  {
    "title": "Halimun\u00a0Salak\u00a0authorities push miners to join conservation effort",
    "source": "https://en.antaranews.com/news/395164/halimunsalakauthorities-push-miners-to-join-conservation-effort",
    "timestamp": "2025-12-04 22:54:00"
  },
  {
    "title": "Indonesia sees slight Q4 growth hit after disasters, minister says",
    "source": "https://en.antaranews.com/news/395158/indonesia-sees-slight-q4-growth-hit-after-disasters-minister-says",
    "timestamp": "2025-12-04 22:22:00"
  },
  {
    "title": "Indonesia seeks expansion of preferential trade agreement with Turkey",
    "source": "https://en.antaranews.com/news/395146/indonesia-seeks-expansion-of-preferential-trade-agreement-with-turkey",
    "timestamp": "2025-12-04 22:06:00"
  },
  {
    "title": "ADB, World Bank launch first projects in Pacific under new framework",
    "source": "https://en.antaranews.com/news/395122/adb-world-bank-launch-first-projects-in-pacific-under-new-framework",
    "timestamp": "2025-12-04 19:52:00"
  },
  {
    "title": "Forty spa-trained Indonesian migrant workers sent\u00a0to Maldives",
    "source": "https://en.antaranews.com/news/395086/forty-spa-trained-indonesian-migrant-workers-sentto-maldives",
    "timestamp": "2025-12-04 17:10:00"
  },
  {
    "title": "Indonesia to declare food self-sufficiency on December 31: minister",
    "source": "https://en.antaranews.com/news/395059/indonesia-to-declare-food-self-sufficiency-on-december-31-minister",
    "timestamp": "2025-12-04 15:54:00"
  },
  {
    "title": "Airlangga sets Rp35 trillion target for 2025 Harbolnas transactions",
    "source": "https://en.antaranews.com/news/395053/airlangga-sets-rp35-trillion-target-for-2025-harbolnas-transactions",
    "timestamp": "2025-12-04 15:30:00"
  },
  {
    "title": "Minister Hartarto moves to counter economic impact of Sumatra floods",
    "source": "https://en.antaranews.com/news/395044/minister-hartarto-moves-to-counter-economic-impact-of-sumatra-floods",
    "timestamp": "2025-12-04 14:41:00"
  },
  {
    "title": "Japan's Nikkei skids in subdued Asia as bets of rate hike grow",
    "source": "https://www.thejakartapost.com/business/2025/12/05/japans-nikkei-skids-in-subdued-asia-as-bets-of-rate-hike-grow.html",
    "timestamp": "2025-12-05 00:00:00"
  },
  {
    "title": "Dollar unfazed even as Fed cut comes back into view",
    "source": "https://www.thejakartapost.com/business/2025/11/25/dollar-unfazed-even-as-fed-cut-comes-back-into-view.html",
    "timestamp": "2025-11-25 00:00:00"
  },
  {
    "title": "Transaksi Makin Mudah, Bayar QRIS Bisa dengan Kartu Kredit BRI",
    "source": "https://emitennews.com/news/transaksi-makin-mudah-bayar-qris-bisa-dengan-kartu-kredit-bri",
    "timestamp": "2025-12-05 00:00:00"
  },
  {
    "title": "Senyap! Batu Investasi Serok 161,89 Juta Saham PGJO",
    "source": "https://emitennews.com/news/senyap-batu-investasi-serok-16189-juta-saham-pgjo",
    "timestamp": "2025-12-05 00:00:00"
  },
  {
    "title": "VICO Eksekusi Private Placement VINS Rp140 per Helai",
    "source": "https://emitennews.com/news/vico-eksekusi-private-placement-vins-rp140-per-helai",
    "timestamp": "2025-12-05 00:00:00"
  },
  {
    "title": "Keponakan Prabowo Akuisisi 20 Persen Saham TRIN",
    "source": "https://emitennews.com/news/keponakan-prabowo-akuisisi-20-persen-saham-trin",
    "timestamp": "2025-12-05 00:00:00"
  },
  {
    "title": "Lego 335,76 Juta Saham DEWA, Investor Ini Raup Rp141 Miliar",
    "source": "https://emitennews.com/news/lego-33576-juta-saham-dewa-investor-ini-raup-rp141-miliar",
    "timestamp": "2025-12-05 00:00:00"
  },
  {
    "title": "Emiten Hapsoro (RATU) Beber Transaksi Baru",
    "source": "https://emitennews.com/news/emiten-hapsoro-ratu-beber-transaksi-baru",
    "timestamp": "2025-12-05 00:00:00"
  },
  {
    "title": "Izin Investor, TRUE Private Placement 757,11 Juta Lembar",
    "source": "https://emitennews.com/news/izin-investor-true-private-placement-75711-juta-lembar",
    "timestamp": "2025-12-05 00:00:00"
  },
  {
    "title": "Saham Beku! Pengendali ARKO Divestasi Jutaan Lembar Harga Miring",
    "source": "https://emitennews.com/news/saham-beku-pengendali-arko-divestasi-jutaan-lembar-harga-miring",
    "timestamp": "2025-12-05 00:00:00"
  },
  {
    "title": "UNVR Tabur Dividen Interim Rp3,3 Triliun, Cek Jadwalnya",
    "source": "https://emitennews.com/news/unvr-tabur-dividen-interim-rp33-triliun-cek-jadwalnya",
    "timestamp": "2025-12-05 00:00:00"
  },
  {
    "title": "KEEN Ditunjuk sebagai Pemenang Tender PLTS Tobelo 10 MW",
    "source": "https://emitennews.com/news/keen-ditunjuk-sebagai-pemenang-tender-plts-tobelo-10-mw",
    "timestamp": "2025-12-05 00:00:00"
  },
  {
    "title": "Surge (WIFI) dan KAI Perluas Koridor Fiber-Optik ke Pulau Sumatra",
    "source": "https://emitennews.com/news/surge-wifi-dan-kai-perluas-koridor-fiber-optik-ke-pulau-sumatra",
    "timestamp": "2025-12-05 00:00:00"
  },
  {
    "title": "Lahir dari Kas Masjid, Ini Cikal Bakal BRI Yang Kini Berusia 130 Tahun",
    "source": "https://emitennews.com/news/lahir-dari-kas-masjid-ini-cikal-bakal-bri-yang-kini-berusia-130-tahun",
    "timestamp": "2025-12-04 00:00:00"
  },
  {
    "title": "Andry Hakim Tambah Koleksi Saham CBRE, Harga Ngikut Naik",
    "source": "https://emitennews.com/news/andry-hakim-tambah-koleksi-saham-cbre-harga-ngikut-naik",
    "timestamp": "2025-12-04 00:00:00"
  },
  {
    "title": "Andalan Sakti (ASPI) Beber Calon Pengendali Mau Kuasai 51,18 Persen",
    "source": "https://emitennews.com/news/andalan-sakti-aspi-beber-calon-pengendali-mau-kuasai-5118-persen",
    "timestamp": "2025-12-04 00:00:00"
  },
  {
    "title": "Kesehatan Keuangan TUGU Lampaui Industri, Cek Saja Buktinya",
    "source": "https://emitennews.com/news/kesehatan-keuangan-tugu-lampaui-industri-cek-saja-buktinya",
    "timestamp": "2025-12-04 00:00:00"
  },
  {
    "title": "Kurangi Porsi di HOPE, Investor Ini Divestasi Tembus Rp20,15 Miliar",
    "source": "https://emitennews.com/news/kurangi-porsi-di-hope-investor-ini-divestasi-tembus-rp2015-miliar",
    "timestamp": "2025-12-04 00:00:00"
  },
  {
    "title": "Benteng Api Technic (BATR) Siap Tangkap Peluang Industri Refraktori",
    "source": "https://emitennews.com/news/benteng-api-technic-batr-siap-tangkap-peluang-industri-refraktori",
    "timestamp": "2025-12-04 00:00:00"
  },
  {
    "title": "Leyand International (LAPD) Beber Aksi Baru",
    "source": "https://emitennews.com/news/leyand-international-lapd-beber-aksi-baru",
    "timestamp": "2025-12-04 00:00:00"
  }
]